README.md
setup.cfg
setup.py
openapi_client/__init__.py
openapi_client/api_client.py
openapi_client/configuration.py
openapi_client/exceptions.py
openapi_client/model_utils.py
openapi_client/rest.py
openapi_client/api/__init__.py
openapi_client/api/destinations_api.py
openapi_client/api/entities_api.py
openapi_client/apis/__init__.py
openapi_client/model/__init__.py
openapi_client/model/boarding_group_state.py
openapi_client/model/destination_entry.py
openapi_client/model/destination_park_entry.py
openapi_client/model/destinations_response.py
openapi_client/model/entity_child.py
openapi_client/model/entity_children_response.py
openapi_client/model/entity_data.py
openapi_client/model/entity_data_location.py
openapi_client/model/entity_live_data.py
openapi_client/model/entity_live_data_response.py
openapi_client/model/entity_schedule_response.py
openapi_client/model/entity_type.py
openapi_client/model/live_queue.py
openapi_client/model/live_queue_boardinggroup.py
openapi_client/model/live_queue_paidreturntime.py
openapi_client/model/live_queue_returntime.py
openapi_client/model/live_queue_standby.py
openapi_client/model/live_show_time.py
openapi_client/model/live_status_type.py
openapi_client/model/price_data.py
openapi_client/model/return_time_state.py
openapi_client/model/schedule_entry.py
openapi_client/model/tag_data.py
openapi_client/models/__init__.py
test/test_boarding_group_state.py
test/test_destination_entry.py
test/test_destination_park_entry.py
test/test_destinations_api.py
test/test_destinations_response.py
test/test_entities_api.py
test/test_entity_child.py
test/test_entity_children_response.py
test/test_entity_data.py
test/test_entity_data_location.py
test/test_entity_live_data.py
test/test_entity_live_data_response.py
test/test_entity_schedule_response.py
test/test_entity_type.py
test/test_live_queue.py
test/test_live_queue_boardinggroup.py
test/test_live_queue_paidreturntime.py
test/test_live_queue_returntime.py
test/test_live_queue_standby.py
themeparks.egg-info/PKG-INFO
themeparks.egg-info/SOURCES.txt
themeparks.egg-info/dependency_links.txt
themeparks.egg-info/requires.txt
themeparks.egg-info/top_level.txt